ddm/__init__.py
ddm/apps.py
ddm/apis/__init__.py
ddm/apis/apps.py
ddm/apis/serializers.py
ddm/apis/urls.py
ddm/apis/views.py
ddm/apis/tests/__init__.py
ddm/apis/tests/test_views.py
ddm/auth/__init__.py
ddm/auth/apps.py
ddm/auth/forms.py
ddm/auth/models.py
ddm/auth/urls.py
ddm/auth/utils.py
ddm/auth/views.py
ddm/auth/migrations/0001_initial.py
ddm/auth/migrations/0002_alter_projectaccesstoken_project.py
ddm/auth/migrations/__init__.py
ddm/auth/templates/ddm_auth/login.html
ddm/auth/templates/ddm_auth/login_oidc.html
ddm/auth/templates/ddm_auth/no_permission.html
ddm/auth/templates/ddm_auth/token.html
ddm/auth/tests/__init__.py
ddm/auth/tests/test_models.py
ddm/auth/tests/test_utils.py
ddm/auth/tests/test_views.py
ddm/core/__init__.py
ddm/core/apps.py
ddm/core/ckeditor_config.py
ddm/core/context_processors.py
ddm/core/urls.py
ddm/core/static/ddm_core/css/ddm-base.css
ddm/core/static/ddm_core/css/ddm-ckeditor-styles.css
ddm/core/static/ddm_core/css/fonts.css
ddm/core/static/ddm_core/css/research-interface-base.css
ddm/core/static/ddm_core/css/bootstrap/bootstrap-icons.css
ddm/core/static/ddm_core/css/bootstrap/bootstrap-table-filter-control.min.css
ddm/core/static/ddm_core/css/bootstrap/bootstrap-table.min.css
ddm/core/static/ddm_core/css/bootstrap/bootstrap.min.css
ddm/core/static/ddm_core/css/bootstrap/bootstrap.min.css.map
ddm/core/static/ddm_core/css/research_interface/ddm-accordion.css
ddm/core/static/ddm_core/css/research_interface/ddm-buttons.css
ddm/core/static/ddm_core/css/research_interface/forms.css
ddm/core/static/ddm_core/css/research_interface/info-collapsible.css
ddm/core/static/ddm_core/css/research_interface/load-spinner.css
ddm/core/static/ddm_core/css/research_interface/message.css
ddm/core/static/ddm_core/css/research_interface/progress-bar.css
ddm/core/static/ddm_core/css/research_interface/utils.css
ddm/core/static/ddm_core/fonts/NunitoSans/NunitoSans-Black.ttf
ddm/core/static/ddm_core/fonts/NunitoSans/NunitoSans-BlackItalic.ttf
django_ddm-2.1.3.dist-info/LICENSE
django_ddm-2.1.3.dist-info/METADATA
django_ddm-2.1.3.dist-info/WHEEL
django_ddm-2.1.3.dist-info/top_level.txt
django_ddm-2.1.3.dist-info/RECORD
