Metadata-Version: 2.1
Name: django-ddm
Version: 2.1.3
Summary: A Django app to setup data donation projects.
Home-page: https://github.com/uzh/ddm
Author: Nico Pfiffner
Author-email: n.pfiffner@ikmz.uzh.ch
License: GPLv3
Project-URL: Documentation, https://uzh.github.io/ddm/
Project-URL: Website, https://datadonation.uzh.ch
Classifier: Environment :: Web Environment
Classifier: Framework :: Django
Classifier: Framework :: Django :: 4.2
Classifier: Intended Audience :: Developers
Classifier: License :: OSI Approved :: GNU General Public License v3 (GPLv3)
Classifier: Operating System :: OS Independent
Classifier: Programming Language :: Python :: 3 :: Only
Classifier: Programming Language :: Python :: 3.8
Classifier: Programming Language :: Python :: 3.11
Requires-Python: >=3.8
License-File: LICENSE
Requires-Dist: Django >=4.2
Requires-Dist: pycryptodome
Requires-Dist: django-ckeditor-5
Requires-Dist: django-polymorphic
Requires-Dist: django-webpack-loader
Requires-Dist: djangorestframework
Requires-Dist: sqlparse
Requires-Dist: asgiref
